additional_lightweight_types/__init__.py
additional_lightweight_types/example.py
additional_lightweight_types-0.0.3.dist-info/LICENCE
additional_lightweight_types-0.0.3.dist-info/METADATA
additional_lightweight_types-0.0.3.dist-info/WHEEL
additional_lightweight_types-0.0.3.dist-info/top_level.txt
additional_lightweight_types-0.0.3.dist-info/RECORD
